{
  "version": "1.0",
  "startDate": "2025-10-21T02:18:23.548Z",
  "lastUpdated": "2025-11-04T21:23:37.470Z",
  "featureHighlights": {
    "Resource Directory": {
      "uses": 8,
      "platforms": {
        "mastodon": 0,
        "bluesky": 8,
        "x": 0
      },
      "timeSlots": {
        "morning": 1,
        "midday": 4,
        "evening": 2,
        "night": 1
      },
      "firstUsed": "2025-10-21T02:18:23.975Z",
      "lastUsed": "2025-11-04T15:29:27.136Z"
    },
    "Benefits Navigator": {
      "uses": 7,
      "platforms": {
        "mastodon": 0,
        "bluesky": 7,
        "x": 0
      },
      "timeSlots": {
        "morning": 2,
        "midday": 1,
        "evening": 3,
        "night": 1
      },
      "firstUsed": "2025-10-21T02:21:47.744Z",
      "lastUsed": "2025-11-03T21:23:43.576Z"
    },
    "News Curation": {
      "uses": 4,
      "platforms": {
        "mastodon": 0,
        "bluesky": 4,
        "x": 0
      },
      "timeSlots": {
        "morning": 3,
        "midday": 0,
        "evening": 1,
        "night": 0
      },
      "firstUsed": "2025-10-21T09:23:50.315Z",
      "lastUsed": "2025-11-01T21:19:46.688Z"
    },
    "Community Resources": {
      "uses": 9,
      "platforms": {
        "mastodon": 0,
        "bluesky": 9,
        "x": 0
      },
      "timeSlots": {
        "morning": 4,
        "midday": 2,
        "evening": 3,
        "night": 0
      },
      "firstUsed": "2025-10-21T20:23:31.438Z",
      "lastUsed": "2025-11-04T21:23:37.470Z"
    },
    "Accessibility Tools": {
      "uses": 10,
      "platforms": {
        "mastodon": 0,
        "bluesky": 10,
        "x": 0
      },
      "timeSlots": {
        "morning": 4,
        "midday": 3,
        "evening": 3,
        "night": 0
      },
      "firstUsed": "2025-10-21T21:22:47.426Z",
      "lastUsed": "2025-11-01T09:19:39.490Z"
    },
    "Provincial Guides": {
      "uses": 6,
      "platforms": {
        "mastodon": 0,
        "bluesky": 6,
        "x": 0
      },
      "timeSlots": {
        "morning": 1,
        "midday": 2,
        "evening": 3,
        "night": 0
      },
      "firstUsed": "2025-10-23T21:20:48.708Z",
      "lastUsed": "2025-10-30T21:22:55.892Z"
    },
    "Multi-language Support": {
      "uses": 4,
      "platforms": {
        "mastodon": 0,
        "bluesky": 4,
        "x": 0
      },
      "timeSlots": {
        "morning": 0,
        "midday": 3,
        "evening": 1,
        "night": 0
      },
      "firstUsed": "2025-10-24T15:27:12.028Z",
      "lastUsed": "2025-10-29T21:23:45.204Z"
    }
  },
  "timeSlots": {
    "night": {
      "posts": 2,
      "avgItems": "0.0",
      "platforms": {
        "mastodon": 0,
        "bluesky": 2,
        "x": 0
      },
      "successRate": 0,
      "totalItems": 0
    },
    "morning": {
      "posts": 15,
      "avgItems": "28.7",
      "platforms": {
        "mastodon": 0,
        "bluesky": 15,
        "x": 0
      },
      "successRate": 0,
      "totalItems": 430
    },
    "midday": {
      "posts": 15,
      "avgItems": "22.1",
      "platforms": {
        "mastodon": 0,
        "bluesky": 15,
        "x": 0
      },
      "successRate": 0,
      "totalItems": 331
    },
    "evening": {
      "posts": 18,
      "avgItems": "36.1",
      "platforms": {
        "mastodon": 0,
        "bluesky": 16,
        "x": 0
      },
      "successRate": 0,
      "totalItems": 649
    }
  },
  "platforms": {
    "mastodon": {
      "posts": 50,
      "successes": 0,
      "failures": 50
    },
    "bluesky": {
      "posts": 50,
      "successes": 48,
      "failures": 2
    },
    "x": {
      "posts": 0,
      "successes": 0,
      "failures": 0
    }
  },
  "totalPosts": 100,
  "successRate": "48.00"
}